Metadata-Version: 2.1
Name: Library-explode
Version: 0.0.1
Summary: Im trying to know how to do libraries in python
Home-page: https://github.com/gog1usss/library
Author: gog1usss
Author-email: greengewot@gmail.com
Project-URL: GitHub, https://github.com/gog1usss
Keywords: files speedfiles
Classifier: Programming Language :: Python :: 3.11
Classifier: License :: OSI Approved :: MIT License
Classifier: Operating System :: OS Independent
Requires-Python: >=3.6
